aws_rag_bot_light/__init__.py
aws_rag_bot_light/aws_opensearch_vector_database.py
aws_rag_bot_light/kustomer.py
aws_rag_bot_light/prompt_library.py
aws_rag_bot_light/rag_chatbot.py
aws_rag_bot_light-0.1.3.dist-info/LICENSE
aws_rag_bot_light-0.1.3.dist-info/METADATA
aws_rag_bot_light-0.1.3.dist-info/WHEEL
aws_rag_bot_light-0.1.3.dist-info/RECORD
