Metadata-Version: 2.1
Name: aws-rag-bot-light
Version: 0.1.3
Summary: 
License: MIT
Author: danjamk
Author-email: dan@risegardens.com
Requires-Python: >=3.11,<4.0
Classifier: License :: OSI Approved :: MIT License
Classifier: Programming Language :: Python :: 3
Classifier: Programming Language :: Python :: 3.11
Classifier: Programming Language :: Python :: 3.12
Requires-Dist: anthropic (>=0.19.2,<0.20.0)
Requires-Dist: boto3 (>=1.34.60,<2.0.0)
Requires-Dist: langchain (>=0.1.11,<0.2.0)
Requires-Dist: opensearch-py (>=2.4.2,<3.0.0)
Requires-Dist: python-dotenv (>=1.0.1,<2.0.0)
Requires-Dist: requests-aws4auth (>=1.2.3,<2.0.0)
